{
  "UseShortFile": false,
  "Appenders": {
    "console": {
      "Type": "console"
    },
    "daylist": {
      "Type": "dailyfile",
      "Target": "/log/daylist.log"
    },
    "dayasin": {
      "Type": "dailyfile",
      "Target": "/log/dayasin.log"
    },
    "dayip": {
      "Type": "dailyfile",
      "Target": "/log/dayip.log"
    }
  },
  "Loggers": {
    "daylist": {
      "Appenders": [
        "console",
        "daylist"
      ],
      "Level": "log"
    },
    "dayasin": {
      "Appenders": [
        "console",
        "dayasin"
      ],
      "Level": "log"
    },
    "dayip": {
      "Appenders": [
        "console",
        "dayip"
      ],
      "Level": "log"
    }
  },
  "Root": {
    "Level": "log",
    "Appenders": [
      "console"
    ]
  }
}